<language>
  <generic>
    <sizes> B, kB, MB, GB, TB</sizes>
  </generic>
  <quarantine>
    <add>Jauna vienība</add>
    <quarantine>Karantīna</quarantine>
    <whitelist>Baltais saraksts</whitelist>
    <blacklist>Melnais saraksts</blacklist>
    <save>Saglabāt</save>
    <cancel>Atcelt</cancel>
    <new_item>Pievienot jaunu e-pastu</new_item>
  </quarantine>
  <settings>
    <disable_shortcuts>Disable shortcuts</disable_shortcuts>
    <enable_swipe_gestures>Enable swipe gestures on touch devices</enable_swipe_gestures>
    <use_high_contrast_skin>Lietot augstas izšķirtspējas apvalku</use_high_contrast_skin>
    <menu_as_text>Rādīt tekstu rīkjoslā ikonu vietā</menu_as_text>
    <change_password>Mainīt paroli</change_password>
    <open_change_password_dialog>Atvērt mainīt paroli dialoglogu</open_change_password_dialog>
    <oldpassword>Vecā parole</oldpassword>
    <newpassword>Jaunā parole</newpassword>
    <confirmpassword>Apstipriniet paroli</confirmpassword>
    <remove>Nodzēst</remove>
    <settings>Iestatījumi</settings>
    <navigate>Administrēt</navigate>
    <user>Mani iestatījumi</user>
    <domain>Domēna administrators</domain>
    <admin>Administratora iestatījumi</admin>
    <new_domain>Jauns domēns</new_domain>
    <test_dropdown>a|b|c|d</test_dropdown>
    <general>Vispārējs</general>
    <layout>Izkārtojums</layout>
    <mail>Pasts</mail>
    <compose>Izveidot</compose>
    <person>E-pasts</person>
    <person_header>Pievienot jaunu no adreses</person_header>
    <person_description>piemēram, &quot;Jānis Bērziņš&quot; &amp;lt;janis.berzins@icewarp.com&amp;gt;</person_description>
    <autoresponder>Automātiskais atbildētājs</autoresponder>
    <forwarder>Pārsūtītājs</forwarder>
    <layout_desc>Izkārtojums, Pasts</layout_desc>
    <compose_desc>Iestatījumi pēc noklusējuma jaunai ziņai (Lasiet apstiprinājumu, HTML/parastais formāts, paraksts).</compose_desc>
    <general_desc>Jūsu pastkastes konfigurēšana pārlūkošanai, dzēšanai un atbildēšanai uz ziņām.</general_desc>
    <personalities_desc>Uzstādīt alternatīvā e-pasta identitātes (dažādi No: adrese) jūsu lietotāja kontam.</personalities_desc>
    <autoresponder_desc>Automātiski atbildēt uz ienākošajām e-pasta ziņām, kad esat atvaļinājumā.</autoresponder_desc>
    <forwarder_desc>Pārsūtīt vai kopēt ienākošās e-pasta ziņas uz jebkuru citu e-pasta adresi</forwarder_desc>
    <date_format>Datuma formāts</date_format>
    <time_format>Laika formāts</time_format>
    <list_count>Vienību sarakstu skaits</list_count>
    <font_family>Fonts pēc noklusējuma</font_family>
    <font_size>Fonta lielums pēc noklusējuma</font_size>
    <text_direction>Teksta virziens</text_direction>
    <text_direction_values>No kreisās uz labo|No labās uz kreiso pusi</text_direction_values>
    <empty_trash_every>Iztukšot miskastes mapi katras</empty_trash_every>
    <days>dienas</days>
    <move_deleted>Pārvietot izdzēstās ziņas uz miskastes mapi</move_deleted>
    <delete_messages_on_empty>Vienmēr dzēst ziņu ar &quot;Iztukšot mapi&quot; darbību</delete_messages_on_empty>
    <add_recipients>Automātiski pievienot ziņu adresātus adrešu grāmatā</add_recipients>
    <group_pref>Grupas tēmas prefiksi (e.g. Re[4], Fw[2])</group_pref>
    <request_read_confirmation>Pieprasīt lasīšanas apstiprinājumu</request_read_confirmation>
    <save_sent_msg>Saglabāt nosūtītās ziņas mapē</save_sent_msg>
    <message_format>Ziņas formāts</message_format>
    <message_format_labels>Vienkāršs|HTML</message_format_labels>
    <signature>Paraksts</signature>
    <forward_to>Pārsūtīt</forward_to>
    <keep_in_inbox>Turēt ziņas iesūtnē</keep_in_inbox>
    <forward_older>Pārsūtīt e-pastu vecāku par</forward_older>
    <forward_older_to>Nosūtīt vecāku e-pastu uz</forward_older_to>
    <ar_mode>Režīms</ar_mode>
    <ar_mode_labels>Atslēgts|Atbildēt vienmēr|Atbildēt vienreiz|Atbildēt atkal pēc perioda</ar_mode_labels>
    <ar_respond_only>Atbildēt tikai uz ziņām, kas nosūtītas uz lietotāja e-pasta adresi</ar_respond_only>
    <ar_respond_again>Atbildēt vēlreiz pēc (dienas)</ar_respond_again>
    <ar_from>No</ar_from>
    <ar_subject>Temats</ar_subject>
    <ar_text>Teksts</ar_text>
    <ar_no_responder_for>Nav atbildētāja priekš</ar_no_responder_for>
    <ar_respond_only_between>Atbildēt tikai tad, ja starp</ar_respond_only_between>
    <email>E-pasts</email>
    <responder>Nav atbildes uz</responder>
    <show_attached_images>Automātiski attēlot pievienotos attēlus</show_attached_images>
    <show_inline_images>Automātiski attēlot ārējos attēlus</show_inline_images>
    <use_reply_prefix>Izmantot atbildes prefiksu (&gt;)</use_reply_prefix>
    <time_format_list_labels>12 stundas|24 stundas</time_format_list_labels>
    <force_admin>Piespiest šo iespēju abiem, domēnam un lietotāja iestatījumiem</force_admin>
    <force_domain>Piespiest šo iespēju lietotāja iestatījumiem</force_domain>
    <to_top>Parakstīties ziņas augšdaļā</to_top>
    <quota>Diska kvota:</quota>
    <section_layout>Vispārīgie izkārtojuma iestatījumi</section_layout>
    <section_mail>Vispārīgie pasta iestatījumi</section_mail>
    <section_autoresponder>Iestatīt automātisko atbildi gadījumā, kad neesat uz vietas.</section_autoresponder>
    <section_norespond>Uz minētajām e-pasta adresēm netika atbildēts.</section_norespond>
    <domains>Domēns</domains>
    <accounts>Konti</accounts>
  </settings>
  <confirmation>
    <delete_mail>Vai tiešām vēlaties dzēst atlasītās ziņas?</delete_mail>
    <blacklist_mail>Vai tiešām vēlaties ievietot melnajā sarakstā atlasītās ziņas?</blacklist_mail>
    <delete_contact>Vai tiešām vēlaties dzēst šo kontaktpersonu?</delete_contact>
    <delete_contact_distribution>Vai tiešām vēlaties dzēst šo adresātu sarakstu?</delete_contact_distribution>
    <delete_event>Vai tiešām vēlaties dzēst atlasītos notikumus?</delete_event>
    <delete_note>Vai tiešām vēlaties dzēst atlasītās piezīmes?</delete_note>
    <delete_task>Vai tiešām vēlaties dzēst atlasītos uzdevumus?</delete_task>
    <delete_personalities>Vai tiešām vēlaties dzēst atlasīto(-ās) vienību(-as)?</delete_personalities>
    <delete_quarantine>Vai tiešām vēlaties dzēst atlasītās vienības?</delete_quarantine>
    <delete_this_mail>Vai tiešām vēlaties dzēst šo ziņu?</delete_this_mail>
    <delete_items>Vai tiešām vēlaties dzēst atlasīto(-ās) vienību(-as)?</delete_items>
    <delete_item>Vai tiešām vēlaties dzēst atlasīto vienību?</delete_item>
  </confirmation>
  <string>
    <no_item>Šajā mapē nav nevienas vienības.</no_item>
  </string>
  <menu>
    <files>Faili</files>
    <notes>Piezīmes</notes>
    <tasks>Uzdevumi</tasks>
    <journal>Žurnāls</journal>
    <calendar>Kalendārs</calendar>
    <search>Meklēt</search>
    <messages>Ziņas</messages>
    <contacts>Kontaktpersonas</contacts>
    <searchBut>Atrast</searchBut>
    <address_book>Adrešu grāmata</address_book>
    <logout>Iziet</logout>
    <help>Palīdzība</help>
    <settings>Iestatījumi</settings>
    <switch>Pārslēgties uz</switch>
    <help_url>language/en/help.html</help_url>
    <quarantine>Filtri</quarantine>
    <alert_restricted_access>Diemžēl piekļuve šai cilnei ir aizliegta</alert_restricted_access>
    <basic>Planšetdatora interfeiss</basic>
    <advanced>Darba virsmas interfeiss</advanced>
    <mobile>Mobilais interfeiss</mobile>
  </menu>
  <tree>
    <add_folder>Pievienot mapi</add_folder>
    <new_message>Jauna ziņa</new_message>
    <manage_folders>Mapju pārvaldīšana</manage_folders>
    <open_folder>Atvērt mapi</open_folder>
    <open>Atvērt</open>
  </tree>
  <mail_view>
    <attachments>Pielikumi</attachments>
    <from>No</from>
    <cc>Cc</cc>
    <bcc>Bcc</bcc>
    <subject>Temats</subject>
    <all_headers>Skatīt visas galvenes</all_headers>
    <all_images>Rādīt attēlus</all_images>
    <next>Nākošais</next>
    <prev>Iepriekšējais</prev>
    <first>Pirmais</first>
    <last>Pēdējais</last>
    <show_external_images>Ārējie resursi ir bloķēti. Noklikšķiniet šeit, lai tos attēlotu.</show_external_images>
    <download_all>Lejupielādēt visu</download_all>
    <detail>Detaļa</detail>
    <blue_box_start>Sākums</blue_box_start>
    <blue_box_end>Beigas</blue_box_end>
    <blue_box_description>Apraksts</blue_box_description>
    <blue_box_accept>Piekrist</blue_box_accept>
    <blue_box_decline>Atteikt</blue_box_decline>
    <blue_box_subscribe_folder>Pierakstīties mapei</blue_box_subscribe_folder>
    <blue_box_subscribe_account>Pierakstīties kontam</blue_box_subscribe_account>
    <item_accept_ok>Vienība pieņemta</item_accept_ok>
    <read>lasīt</read>
    <write>rakstīt</write>
    <modify>Modificēt</modify>
    <delete>dzēst</delete>
    <administer>administrēt</administer>
    <folder_rights>Mapes piekļuves tiesības</folder_rights>
    <items_rights>Vienības tiesības</items_rights>
  </mail_view>
  <login>
    <send>Sūtīt</send>
    <ip_check>Izslēgt paplašināto drošību</ip_check>
    <user>Lietotājs</user>
    <email>E-pasts</email>
    <password>Parole</password>
    <remember>Atcerēties</remember>
    <language>Valoda</language>
    <allways_ask>Vienmēr jautāt</allways_ask>
    <username>Lietotājvārds</username>
    <username_and_password>Lietotājvārds un parole</username_and_password>
    <auto_login>Automātiskā pieteikšanās</auto_login>
    <login>Pieteikšanās</login>
    <copyright>Powered by IceWarp &lt;a href=&quot;http://www.icewarp.com&quot;&gt;Server&lt;/a&gt; © 1999-2018&lt;br /&gt; Version: $1</copyright>
    <welcome>Esiet sveicināts IceWarp WebKlienta planšetē</welcome>
    <public_welcome>Esiet sveicināts IceWarp publiskajā kalendārā</public_welcome>
    <title>IceWarp WebKlienta planšete</title>
    <public_title>IceWarp publiskais kalendārs</public_title>
    <reset_password>Atkārtoti ievadīt paroli</reset_password>
    <sign_up>Reģistrēties</sign_up>
    <email>E-pasts</email>
    <domain>Domēns</domain>
    <new_password>Jauna parole</new_password>
    <confirm_password>Apstiprināt paroli</confirm_password>
    <full_name>Pilns vārds</full_name>
    <alternative_email>Alternatīvais e-pasts</alternative_email>
    <switch>Pārslēgties uz &lt;a href=&quot;../&quot;&gt;Darba virsmas&lt;/a&gt; vai &lt;a href=&quot;../pda&quot;&gt;Mobilais&lt;/a&gt; Interfeiss.</switch>
    <no_javascript>&lt;b&gt;JavaScript pašlaik ir atslēgts. &lt;/b&gt;&lt;/div&gt;Resultātā, jūs tiekat novirzīts uz WebKlienta planšetes interfeisu, kas piedāvā ierobežotu funkcionalitāti. Ja vēlaties izmantot WebKlienta darbvirsmas interfeisu, lūdzu, apmeklējiet mūsu &lt;a href=&quot;http://esupport.icewarp.com/index.php?/default_import/Knowledgebase/Article/View/194/0/how-to-enable-java-scripting-in-your-browser&quot;&gt;zināšanu bāze&lt;/a&gt; instrukcijas par to, kā to ieslēgt jūsu pārlūkprogrammā&lt;br /&gt;Ja jūsu pārlūkprogramma neatbalsta JavaScript, lūdzu, lejupielādējiet jaunāko versiju &lt;a href=&quot;http://www.microsoft.com/windows/downloads/ie/getitnow.mspx&quot;&gt;Internet Explorer&lt;/a&gt; vai &lt;a href=&quot;http://www.getfirefox.com&quot;&gt;Mozilla FireFox.&lt;/a&gt;</no_javascript>
    <captcha>Captcha</captcha>
    <word>Ierakstiet kodu no attēla</word>
  </login>
  <files>
    <add>Augšupielādēt failu</add>
    <download>Lejupielādēt</download>
    <file>Fails</file>
  </files>
  <file_list>
    <filename>Faila nosaukums</filename>
    <description>Apraksts</description>
    <modified>Pārveidot</modified>
    <size>Izmērs</size>
    <tags>Atzīmes</tags>
  </file_list>
  <notes>
    <category>Kategorija</category>
    <add>Jauna piezīme</add>
  </notes>
  <notes_detail>
    <note>Piezīme</note>
    <tags>Atzīmes</tags>
  </notes_detail>
  <tasks_main>
    <add>Jauns uzdevums</add>
  </tasks_main>
  <tasks_detail>
    <task>Uzdevums</task>
    <status>Statuss</status>
    <complete>Pabeigt</complete>
    <priority>Prioritāte</priority>
    <not_started>Nav sācies</not_started>
    <in_progress>Notiek</in_progress>
    <completed>Pabeigts</completed>
    <deferred>Atlikts</deferred>
    <waiting_for_someone_else>Gaida kādu citu</waiting_for_someone_else>
    <medium>Vidējs</medium>
    <high>Augsts</high>
    <low>Zems</low>
    <tags>Atzīmes</tags>
  </tasks_detail>
  <grid_task>
    <start_date>Sākuma datums</start_date>
    <due_date>Izpildes datums</due_date>
  </grid_task>
  <mail_main>
    <fullscreen>Pilnekrāna</fullscreen>
    <subject>Temats</subject>
    <no_subject>Nav temata</no_subject>
    <no_address>Nav adreses</no_address>
    <from>No</from>
    <date>Datums</date>
    <size>Izmērs</size>
    <delete>Dzēst</delete>
    <reply>Atbildēt</reply>
    <reply_to_all>Atbildēt visiem</reply_to_all>
    <forward>Pārsūtīt</forward>
    <print>Drukāt</print>
    <whitelist>Baltais saraksts</whitelist>
    <blacklist>Melnais saraksts</blacklist>
    <dws>Darbība</dws>
    <copy>Kopēt</copy>
    <move>Pārvietot</move>
    <copy_to_folder>Kopēt uz mapi:</copy_to_folder>
    <move_to_folder>Pārvietot uz mapi:</move_to_folder>
    <mar>Atzīmēt kā lasītu</mar>
    <mau>Atzīmēt kā nelasītu</mau>
    <select>Atlasīt</select>
    <all>Visu</all>
    <none>Neviens</none>
    <read>Lasīts</read>
    <unread>Neizlasīts</unread>
    <invert>Izvēlēties pretēji</invert>
    <doit>Lietot</doit>
    <to>Kam</to>
    <fast_reply>Ātrā atbilde</fast_reply>
    <send_message>Sūtīt ziņu</send_message>
    <src>Sūtītājs ir pieprasījis atbildi, lai norādītu, ka esat izlasījis šo ziņu. Vai jūs vēlaties to nosūtīt?</src>
    <save>Saglabāt</save>
    <select_folder>Izvēlieties mapi</select_folder>
    <deliver>Piegādāt</deliver>
    <text>Teksts</text>
    <received>Saņemts</received>
    <saved>Saglabāti</saved>
    <sender>Sūtītājs</sender>
    <owner>Īpašnieks</owner>
    <domain>Domēns</domain>
    <show_all>Rādīt visu</show_all>
  </mail_main>
  <event_list>
    <title>Virsraksts</title>
    <start>Sākums</start>
    <end>Beigas</end>
    <tags>Atzīmes</tags>
  </event_list>
  <event_detail>
    <tags>Atzīmes</tags>
    <show_as>Rādīt kā</show_as>
    <free>Brīvs</free>
    <tentative>Pagaidu</tentative>
    <busy>Aizņemts</busy>
    <out_of_office>Nav uz vietas</out_of_office>
    <title>Virsraksts</title>
    <location>Atrašanās vieta</location>
    <label>Apzīmējums</label>
    <none>Neviens</none>
    <important>Svarīgs</important>
    <business>Darbs</business>
    <personal>Privāts</personal>
    <vacation>Atvaļinājums</vacation>
    <must_attend>Jāapmeklē</must_attend>
    <travel_required>Nepieciešams ceļot</travel_required>
    <needs_preparation>Nepieciešama sagatavošanās</needs_preparation>
    <birthday>Dzimšanas diena</birthday>
    <anniversary>Gadadiena</anniversary>
    <phone_call>Tālruņa zvans</phone_call>
    <category>Kategorija</category>
    <private>Privāts</private>
    <from>No</from>
    <to>Kam</to>
    <notes>Piezīmes</notes>
    <allday>Visas dienas notikums</allday>
    <event>Notikums</event>
    <minutes>Minūte(-s)</minutes>
    <hours>Stunda(-s)</hours>
    <days>Diena(-s)</days>
    <remind_me>Atgādināt man</remind_me>
    <before>pirms</before>
    <no_repeating>Neatkārtot</no_repeating>
    <daily>Ik dienu</daily>
    <weekly>Ik nedēļu</weekly>
    <monthly>Ik mēnesi</monthly>
    <yearly>Ik gadu</yearly>
    <end_date>Beigu datums</end_date>
    <no_end_date>Nav beigu datuma</no_end_date>
    <repeat>Atkārtot</repeat>
    <every>Katru</every>
    <every_workday>Katru darba dienu</every_workday>
    <recur_every>Atkārtoties katru</recur_every>
    <weeks>nedēļa(-s)</weeks>
    <on>on</on>
    <monday>Pirmdiena</monday>
    <tuesday>Otrdiena</tuesday>
    <wednesday>Trešdiena</wednesday>
    <thursday>Ceturtdiena</thursday>
    <friday>Piektdiena</friday>
    <saturday>Sestdiena</saturday>
    <sunday>Svētdiena</sunday>
    <day>Diena</day>
    <months>mēnesis(-ši)</months>
    <first>Pirmais</first>
    <second>Otrais</second>
    <third>Trešais</third>
    <fourth>Ceturtais</fourth>
    <last>Pēdējais</last>
    <week>Nedēļa</week>
    <work_week>Darba nedēļa</work_week>
    <weekend>Nedēļās nogale</weekend>
    <of_every>katru</of_every>
    <of>no</of>
    <years>gads(-i)</years>
    <the>The</the>
    <times>reizes</times>
    <count>skaits</count>
    <until>līdz</until>
    <tags>Atzīmes</tags>
  </event_detail>
  <event_main>
    <mon>Pr</mon>
    <tue>Ot</tue>
    <wed>Tr</wed>
    <thu>Ce</thu>
    <fri>Pk</fri>
    <sat>Se</sat>
    <sun>Sv</sun>
    <jan>Janvāris</jan>
    <feb>Februāris</feb>
    <mar>Marts</mar>
    <apr>Aprīlis</apr>
    <may>Maijs</may>
    <jun>Jūnijs</jun>
    <jul>Jūlijs</jul>
    <aug>Augusts</aug>
    <sep>Septembris</sep>
    <oct>Oktobris</oct>
    <nov>Novembris</nov>
    <dec>Decembris</dec>
    <week>Nedēļa</week>
    <week_view>Nedēļa</week_view>
    <work_week_view>Darba nedēļa</work_week_view>
    <month_view>Mēnesis</month_view>
    <day_view>Diena</day_view>
    <list>Ierakstīt sarakstā</list>
    <add>Jauns notikums</add>
    <save>Saglabāt</save>
    <no_title>Nav nosaukuma</no_title>
    <search>Meklēt:</search>
    <account>Konts:</account>
    <print>Drukāt</print>
  </event_main>
  <contact_main>
    <contact>Kontaktpersona</contact>
    <distribution_list>Adresātu saraksts</distribution_list>
    <title>Virsraksts</title>
    <no_email>Nav e-pasta</no_email>
    <card_view>Kartes skats</card_view>
    <list_view>Saraksta skats</list_view>
    <contact_name>Kontaktpersonas vārds</contact_name>
    <email>E-pasts</email>
    <company>Uzņēmums</company>
    <job>Nodarbošanās</job>
    <department>Departaments</department>
    <profession>Profesija</profession>
    <category>Kategorija</category>
    <general>Vispārējs</general>
    <first_name>Vārds</first_name>
    <middle_name>Otrais vārds</middle_name>
    <last_name>Uzvārds</last_name>
    <nick>Segvārds</nick>
    <sort_string>Kārtošanas virkne</sort_string>
    <title>Virsraksts</title>
    <suffix>Sufikss</suffix>
    <category>Kategorija</category>
    <web>Tīmekļa vietne</web>
    <street>Iela</street>
    <city>Pilsēta</city>
    <zip>ZIP</zip>
    <state>Štats</state>
    <country>Valsts</country>
    <im>IM</im>
    <phones>Tālruņi</phones>
    <work>Darba</work>
    <home>Mājas</home>
    <assistant>Asistents</assistant>
    <fax_home>Fakss mājās</fax_home>
    <fax_work>Fakss darbā</fax_work>
    <call_back>Atzvanīt</call_back>
    <company>Uzņēmums</company>
    <car>Automāšīna</car>
    <isdn>ISDN</isdn>
    <mobile>Mobilais</mobile>
    <other>Cits</other>
    <other_fax>Cits fakss</other_fax>
    <pager>Peidžers</pager>
    <primary>Galvenais</primary>
    <radio>Radio</radio>
    <telex>Telekss</telex>
    <hearing>Dzirdamība</hearing>
    <add>Jauna kontaktpersona</add>
    <notes>Piezīmes</notes>
    <no_name>Nav kontaktpersonas vārda</no_name>
    <select>Izvēlēties veidu</select>
    <select_contacts>Atlasiet kontaktpersonas, kuras vēlaties pievienot</select_contacts>
    <add_distribution>Jauns adresātu saraksts</add_distribution>
    <add_new>Pievienot</add_new>
    <add_item_distribution>Pievienot no adrešu grāmatas</add_item_distribution>
    <save>Saglabāt</save>
    <edit>Rediģēt</edit>
    <edit_selected>Rediģēt atlasīto</edit_selected>
    <delete_selected>Dzēst</delete_selected>
    <cancel>Atcelt</cancel>
    <onleave_warning>Vai vēlaties iziet? Visi nesaglabātie dati tiks zaudēti.</onleave_warning>
    <tags>Atzīmes</tags>
  </contact_main>
  <hipaa>
    <new_patient>Jauns pacients</new_patient>
    <new_staff>Jauns darbinieks</new_staff>
    <notify_email>Ziņot pa e-pastu</notify_email>
    <notify_sms>Ziņot ar SMS</notify_sms>
  </hipaa>
  <hippa_detail>
    <add>Jauns</add>
    <staff>Personāls</staff>
    <patient>Pacients</patient>
  </hippa_detail>
  <grid>
    <title>Virsraksts</title>
    <note>Piezīme</note>
    <size>Izmērs</size>
    <category>Kategorija</category>
    <start>Sākums</start>
    <end>Beigas</end>
    <save>Saglabāt</save>
    <cancel>Atcelt</cancel>
    <number_of_items>Number of items selected on other pages:</number_of_items>
    <clear>Clear</clear>
  </grid>
  <mail_compose>
    <select_text>Lūdzu, atlasiet tekstu, kuru vēlaties izveidot kā hipersaiti.</select_text>
    <enter_url>Ievadiet URL šai saitei:</enter_url>
    <image_location>Ievadiet šī attēla atrašanās vietu:</image_location>
    <image_alt>Ievadiet alternatīvo tekstu šim attēlam:</image_alt>
    <image>Ievietot attēlu</image>
    <htmlsource>HTML avots</htmlsource>
    <hyperlink>Hipersaite</hyperlink>
    <underline>Pasvītrot</underline>
    <italic>Kursīvs</italic>
    <bold>Treknraksts</bold>
    <fontsize>Fonta lielums</fontsize>
    <fontformat>Fonta formāts</fontformat>
    <outdent>Samazināt atkāpi</outdent>
    <indent>Palielināt atkāpi</indent>
    <orderedlist>Numurēts saraksts</orderedlist>
    <unorderedlist>Saraksts ar aizzīmēm</unorderedlist>
    <justify>Izlīdzināt</justify>
    <right>Līdzināt pa labi</right>
    <center>Līdzināt uz centru</center>
    <left>Līdzināt pa kreisi</left>
    <blockformat>Bloķēts formatējums</blockformat>
    <block_type>Bloķēts veids</block_type>
    <heading>Virsraksts</heading>
    <paragraph>Rindkopa</paragraph>
    <size>Izmērs</size>
    <font>Fonts</font>
    <cancel>Atcelt</cancel>
    <email>E-pasts</email>
    <options>Iespējas</options>
    <plain>Vienkāršs</plain>
    <html>HTML</html>
    <from>No</from>
    <to>Kam</to>
    <cc>Cc</cc>
    <bcc>Bcc</bcc>
    <subject>Temats</subject>
    <date>Datums</date>
    <attachments>Pielikumi</attachments>
    <text>Teksts</text>
    <send_message>Sūtīt ziņu</send_message>
    <save_message>Saglabāt</save_message>
    <br/>
    <spellchecker>Valodas pareizrakstības pārbaudītājs</spellchecker>
    <rrc>Pieprasīt lasīšanas apliecinājumu</rrc>
    <ssm>Saglabāt nosūtītās ziņas mapē</ssm>
    <psa>Izmanot SmartAttach</psa>
    <priority>Prioritāte</priority>
    <lowest>Zemākais</lowest>
    <low>Zems</low>
    <normal>Normāls</normal>
    <high>Augsts</high>
    <highest>Augstākais</highest>
    <rta>Atbildēt uz adresi</rta>
    <charset>Rakstzīmju kopa</charset>
    <auto>Automātiski</auto>
    <original_message>-----Pārsūtītā vēstule-----</original_message>
    <read_confirmation_subject>Lasīt: %SUBJECT%</read_confirmation_subject>
    <read_confirmation_text>Jūsu ziņa ir izlasīta. &#13;&#10;&#13;&#10;Ziņas detaļas:&#13;&#10;&#13;&#10;No: %FROM%&#13;&#10;Kam: %TO%&#13;&#10;Datums: %DATE%&#13;&#10;Temats: %SUBJECT%</read_confirmation_text>
    <add_contacts>Pievienot kontaktpersonas</add_contacts>
    <add_files>Pievienot failus</add_files>
    <add_files_from_folder>Add files from folder</add_files_from_folder>
    <add_files_from_dropbox>Add files from Dropbox</add_files_from_dropbox>
    <leave_notice>Vai vēlaties iziet? Ziņa tiks zaudēta.</leave_notice>
    <alias>Aizstājvārds</alias>
  </mail_compose>
  <manage_folders>
    <add>Jauna mape</add>
    <delete>Dzēst</delete>
    <link>Saite</link>
    <unlink>Atvienot</unlink>
    <create_folder>Izveidot jaunu mapi</create_folder>
    <create>Izveidot</create>
    <delete_confirmation_text>Vai tiešām vēlaties neatgriezeniski dzēst šo mapi?</delete_confirmation_text>
    <empty_confirmation_text>Vai tiešām vēlaties neatgriezeniski dzēst vienības šajā mapē?</empty_confirmation_text>
    <delete_yes>Jā</delete_yes>
    <delete_no>Nē</delete_no>
    <link_as>Saistīt mapi kā</link_as>
    <unlink_as>Dzēst / Pārdēvēt mapes saiti</unlink_as>
    <unlink_confirmation_text>Vai tiešām vēlaties dzēst mapes saiti?</unlink_confirmation_text>
    <unlink_yes>Jā</unlink_yes>
    <unlink_no>Nē</unlink_no>
    <virtual>Virtuālā mape</virtual>
    <delete_empty_folder>Dzēst vai iztukšot mapi</delete_empty_folder>
    <edit>Rediģēt</edit>
    <empty>Iztukšot</empty>
    <rename_folder>Pārdēvēt mapi</rename_folder>
    <save>Saglabāt</save>
    <rename>Pārdēvēt</rename>
    <perform_action>Veikt darbību</perform_action>
    <select_folder>Izvēlieties mapi, lai pārvaldītu</select_folder>
    <open_folder>Atvērt mapi</open_folder>
    <open_folder_des>Izmantojiet to, lai piekļūtu mapes saturam.</open_folder_des>
    <link_folder>Saistīt mapi</link_folder>
    <link_folder_des>Izmantojiet to, lai izveidotu saīsni kreisajā izvēlnē priekš mapes kokā.</link_folder_des>
    <add_folder>Pievienot mapi</add_folder>
    <add_folder_dis>Izmantojiet to, lai izveidotu jaunu mapi, kas atrodas atlasītajā mapē.</add_folder_dis>
    <rename_folder_des>Izmantojiet to, lai pārdēvētu izvēlēto mapi.</rename_folder_des>
    <remove_folder>Nodzēst mapi</remove_folder>
    <remove_folder_des>Izmantojiet to, lai pavisam iztukšot un dzēst atlasīto mapi. Brīdinājums: šo darbību nevar atsaukt!</remove_folder_des>
    <default_folder>Iestatīt kā mapi pēc noklusējuma</default_folder>
    <default_folder_des>Izmantojiet to, lai iestatītu šo mapi kā pēc noklusējuma.</default_folder_des>
    <set_default>Iestatīt šo mapi kā pēc noklusējuma</set_default>
    <set>Iestatīt</set>
    <as_drafts>Melnraksti</as_drafts>
    <as_sent>Nosūtīts</as_sent>
    <as_trash>Miskaste</as_trash>
    <set_as_default>Iestatīt</set_as_default>
    <link_first>Mape ir jāpiesaista, pirms to var iestatīt kā pēc noklusējuma.</link_first>
  </manage_folders>
  <common_folders>
    <inbox>Inbox</inbox>
    <drafts>Melnraksti</drafts>
    <sent>Nosūtīts</sent>
    <trash>Miskaste</trash>
  </common_folders>
  <common>
    <yes>Jā</yes>
    <no>Nē</no>
  </common>
  <folder_types>
    <mail>Pasts</mail>
    <contact>Kontaktpersona</contact>
    <event>Kalendārs</event>
    <journal>Žurnāls</journal>
    <note>Piezīme</note>
    <task>Uzdevums</task>
    <file>Fails</file>
    <rss>RSS</rss>
  </folder_types>
  <exceptions>
    <login_invalid_keypair>RSA validation failed. Try again.</login_invalid_keypair>
    <divtcha_confirmation>Nepareizs captcha kods</divtcha_confirmation>
    <missing_values_text>Tukšs teksta ievadē</missing_values_text>
    <missing_values_email>Tukšs e-pasta ievadē</missing_values_email>
    <invalid_email>Invalid email address</invalid_email>
    <password_not_changed>Jaunā parole nedrīkst būt vienāda ar veco paroli</password_not_changed>
    <reset_password_invalid_hashid>Nepareizs jaukšanas ID</reset_password_invalid_hashid>
    <reset_password_uid_file>UID fails nepastāv</reset_password_uid_file>
    <account_alternative_email>Kontam nav alternatīvā e-pasta adrese</account_alternative_email>
    <migration_in_progress>Notiek konta migrācija, lūdzu, mēģiniet vēlreiz vēlāk</migration_in_progress>
    <login_ip_invalid>Pieteikšanās IP ierobežojums: %s</login_ip_invalid>
    <unauthorized>Nesankcionēta piekļuve</unauthorized>
    <folder_type_restricted>Šis mapes veids tika ierobežots ar administratoru</folder_type_restricted>
    <account_does_not_exists>Norādītais konts nepastāv</account_does_not_exists>
    <account_invalid_id>Nevar iegūt kontu %s</account_invalid_id>
    <account_unknown_protocol>Nezināms konts protokols</account_unknown_protocol>
    <account_missing_tag>Kontam trūkst atzīme %s</account_missing_tag>
    <account_missing_id>Trūkst konta ID</account_missing_id>
    <account_invalid_action>Konta darbība ir nepareiza</account_invalid_action>
    <account_already_exists>Konts %s jau pastāv</account_already_exists>
    <account_no_username>Konta lietotājvārds trūkst vai ir tukšs</account_no_username>
    <account_no_password>Konta parole trūkst vai ir tukšs</account_no_password>
    <account_bad_password>Vecā parole ir ievadīta nepareizi</account_bad_password>
    <account_password_policy>Parole neatbilst paroļu politikai</account_password_policy>
    <account_sync>Konta sinhronizācija neizdevās kontam %s</account_sync>
    <account_primary_delete>Nevar izdzēst galveno kontu</account_primary_delete>
    <account_test_failed>Konta tests neizdevās kontam %s</account_test_failed>
    <account_signup_disabled>Reģistrēšanās ir atslēgta</account_signup_disabled>
    <account_signup_error>Konta reģistrēšanas kļūda: %s</account_signup_error>
    <account_signup_1>Nedefinēta kļūda</account_signup_1>
    <account_signup_2>Nepietiekamas licences</account_signup_2>
    <account_signup_3>Parametru izmērs ir par īsu</account_signup_3>
    <account_signup_4>Funkcijas traucējumi</account_signup_4>
    <account_signup_5>Konfigurācija nav atrasta</account_signup_5>
    <account_signup_6>Paroles politika</account_signup_6>
    <account_signup_7>Konts jau pastāv</account_signup_7>
    <account_signup_8>Nepareizas rakstzīmes</account_signup_8>
    <attachment_too_large>Pielikums ir pārāk liels: %s</attachment_too_large>
    <password_confirmation>Paroles neatbilstība</password_confirmation>
    <missing_values>Paroles neatbilstība</missing_values>
    <addon_copy>Nevar kopēt pievienojum-programmu</addon_copy>
    <attachment_file_not_found>Nevar pievienot failu</attachment_file_not_found>
    <attachment_add>Neizdevās pievienot pielikumu</attachment_add>
    <attachment_get>Nevar iegūt pielikumu %s</attachment_get>
    <attacment_class_unknown>Nezināma pielikuma klase</attacment_class_unknown>
    <auth_missing_tag>Autentifikācijai trūkst atzīme %s</auth_missing_tag>
    <auth_export_key_private>Nevar eksportēt personīgo atslēgu</auth_export_key_private>
    <auth_invalid_char>Nepareiza zīme personīgajā atslēgā</auth_invalid_char>
    <confirmation_uid>Captcha sesija nav atrasta</confirmation_uid>
    <confirmation_word_mismatch>Captcha nepareizi ievadīts</confirmation_word_mismatch>
    <db_auto_create>Nevar automātiski izveidot datu bāzi</db_auto_create>
    <db_create_sqlitefile>Nevar izveidot SQLite DB failu</db_create_sqlitefile>
    <db_create_tables>Nevar izveidot tabulas</db_create_tables>
    <db_statement_prepare>Nevar sagatavot paziņojumu</db_statement_prepare>
    <db_invalid_statement>Nepareizs paziņojuma veids</db_invalid_statement>
    <flags_unknown_field>Atzīmju lauks nepareizs</flags_unknown_field>
    <folder_autocreate_failed>Mape %s jau pastāv</folder_autocreate_failed>
    <folder_already_exists>Mape %s jau pastāv</folder_already_exists>
    <folder_does_not_exist>Mape %s neeksistē</folder_does_not_exist>
    <folder_name_bad_char>Speciālās rakstzīmes nav atļautas mapes nosaukumā</folder_name_bad_char>
    <folder_name_length>Nevar iegūt mapes nosaukuma garumu</folder_name_length>
    <folder_name_too_long>Jaunais mapes nosaukums ir pārāk garš</folder_name_too_long>
    <folder_get_list>Nevar iegūt sarakstu ar mapēm</folder_get_list>
    <folder_delete>Nevar dzēst mapi %s</folder_delete>
    <folder_create>Nevar izveidot mapi %s</folder_create>
    <folder_rename_empty>Nevar pārdēvēt mapi ar tukšu nosaukumu</folder_rename_empty>
    <folder_move_to_self>Nevar pārvietot mapi uz sevi</folder_move_to_self>
    <folder_move_to_subfolder>Nevar pārvietot mapi uz tās apakšmapi</folder_move_to_subfolder>
    <folder_rename>Nevar pārdēvēt mapi</folder_rename>
    <folder_copy>Nevar kopēt mapi</folder_copy>
    <folder_empty>Nevar iztukšot mapi</folder_empty>
    <folder_missing_tag>Trūkst mapes atzīme %s</folder_missing_tag>
    <folder_missing_account_id>Mapē trūkst konta ID</folder_missing_account_id>
    <folder_invalid_account_id>Mapei ir nepareizs konta ID %s</folder_invalid_account_id>
    <folder_missing_id>Trūkst mapes ID</folder_missing_id>
    <folder_missing_name>Trūkst mapes nosaukums</folder_missing_name>
    <folder_invalid_action>Nepareiza mapes darbība %s</folder_invalid_action>
    <folder_invalid_type>Nepareizs mapes veids %s</folder_invalid_type>
    <folder_sync>Nevar sinhronizēt mapi %s</folder_sync>
    <folder_empty_non_mail>Nevar iztukšot bez e-pasta mapi</folder_empty_non_mail>
    <folder_insufficient_rights>Nepietiekamas tiesības, lai veiktu šo darbību</folder_insufficient_rights>
    <folder_mark_non_mail>Mēģina iestatīt atzīmes bez e-pasta mapei</folder_mark_non_mail>
    <freebusy_missing_tag>Trūkst brīvs/aizņemts atzīmes %s</freebusy_missing_tag>
    <group_open>Nevar atvērt grupu %s</group_open>
    <group_subscribe>Nevar pierakstīties grupai %s</group_subscribe>
    <group_add>Nevar izveidot grupu</group_add>
    <group_edit>Nevar rediģēt grupu %s</group_edit>
    <group_user_add>Nevar pievienot lietotājus grupai %s</group_user_add>
    <group_user_edit>Nevar rediģēt grupas lietotāju %s</group_user_edit>
    <group_user_delete>Nevar dzēst grupas lietotāju %s</group_user_delete>
    <groupware_upgrade_task>GroupWare pakalpojuma atjaunināšanas procedūra darbojas. Lūdzu, mēģiniet vēlreiz vēlāk.</groupware_upgrade_task>
    <folder_open>Nevar atvērt grupu %s</folder_open>
    <call_open_folder_first>GroupWare mapi nevar atvērt darbībā, kur nepieciešams</call_open_folder_first>
    <call_open_group_first>GroupWare grupu nevar atvērt darbībā, kur nepieciešams</call_open_group_first>
    <subscribe_account_gw>Konta pierakstīšanās kļūda</subscribe_account_gw>
    <unsubscribe_account_gw>Konta atrakstīšanās kļūda</unsubscribe_account_gw>
    <imap_clone>Nevar klonēt IMAP objektu</imap_clone>
    <imap_open>Nevar atvērt IMAP plūsmu</imap_open>
    <imap_internal>IMAP iekšējā kļūda: %s</imap_internal>
    <imap_delimiter_retrieval>IMAP ielādētu atdalītāju kļūda</imap_delimiter_retrieval>
    <imap_getmailboxes>Nevar iegūt pastkastu sarakstu</imap_getmailboxes>
    <imap_mailbox_create>IMAP izveidotā pastkaste %s izveidota</imap_mailbox_create>
    <imap_mailbox_subscribe>Nevar pierakstīties pastkastei %s</imap_mailbox_subscribe>
    <imap_mailbox_delete>Nevar izdzēst pastkasti %s</imap_mailbox_delete>
    <imap_mailbox_unsubscribe>Nevar atrakstīties no pastkastes %s</imap_mailbox_unsubscribe>
    <imap_mailbox_rename>IMAP pastkastes %s pārdēvēšana neizdevās</imap_mailbox_rename>
    <imap_mailbox_delete_items>IMAP pastkastes vienību dzēšana</imap_mailbox_delete_items>
    <imap_mailbox_empty_folder>IMAP pastkastes tukšās vienības</imap_mailbox_empty_folder>
    <imap_mailbox_copyitems>IMAP vienību kopēšana neizdevās</imap_mailbox_copyitems>
    <imap_mailbox_moveitems>IMAP vienību pārvietošana neizdevās</imap_mailbox_moveitems>
    <imap_mailbox_open>Nevar atkārtoti atvērt pastkasti %s</imap_mailbox_open>
    <imap_mailbox_message_list>Nevar saņemt ziņu sarakstu</imap_mailbox_message_list>
    <imap_message_details>Nevar iegūt informāciju par ziņu %s</imap_message_details>
    <imap_no_headers>Nevar iegūt ziņas galvenes %s</imap_no_headers>
    <imap_no_body>Nevar iegūt ziņas saturu %s</imap_no_body>
    <imap_message_create>Nevar pievienot ziņu</imap_message_create>
    <imap_message_delete>Nevar dzēst ziņu %s</imap_message_delete>
    <imap_message_copy>Nevar kopēt ziņu %s</imap_message_copy>
    <imap_message_move>Nevar pārvietot ziņu %s</imap_message_move>
    <imap_flags_set>Nevar iestatīt ziņai %s atzīmes</imap_flags_set>
    <imap_flags_clear>Nevar noņemt ziņai %s atzīmes</imap_flags_clear>
    <imap_message_not_found>Jauna ziņa nav atrasta galamērķa pastkastē</imap_message_not_found>
    <subscribe_account_imap>Kļūda, pierakstoties kontam</subscribe_account_imap>
    <unsubscribe_account_imap>Kļūda konta atrakstīšanās laikā</unsubscribe_account_imap>
    <import_vcalendar>Importēt vCalendar neizdevās</import_vcalendar>
    <import_vcard>Importēt vCard neizdevās</import_vcard>
    <import_missing_tag>Trūkst importēšanas atzīme %s</import_missing_tag>
    <import_missing_action>Trūkst importēšanas darbības</import_missing_action>
    <import_invalid_action>Nepareiza importēšanas darbība %s</import_invalid_action>
    <import_missing_account_id>Trūkst importēšanas konta ID</import_missing_account_id>
    <import_invalid_account_id>Nepareizs importēšanas konta ID</import_invalid_account_id>
    <import_missing_folder_id>Trūkst importēšanas mapes ID</import_missing_folder_id>
    <import_invalid_folder_id>Importēšanai nepareizs mapes ID</import_invalid_folder_id>
    <import_invalid_item_id>Importēšanai nepareizs vienības ID</import_invalid_item_id>
    <import_add_items>Nevar izveidot vienības (saraksts)</import_add_items>
    <import_invalid_data>Mēģina importēt neatbalstītus datus</import_invalid_data>
    <export_invalid_account>Mēģina eksportēt neeksistējošu kontu</export_invalid_account>
    <imip_versit_convert>iMIP versit konversija</imip_versit_convert>
    <imip_versit_empty>iMIP versit tukšs</imip_versit_empty>
    <imip_missing_folder>Trūkst iMIP mape</imip_missing_folder>
    <inputstream_no_xml_input>XML nav nodots ievadei</inputstream_no_xml_input>
    <inputstream_corrupted_input>Bojāta XML ievade</inputstream_corrupted_input>
    <item_invalid_id>Nav vienības ID</item_invalid_id>
    <item_count>Nevar iegūt vienību skaitu</item_count>
    <item_create>Nevar izveidot vienību</item_create>
    <item_delete>Vienība %s nevar tikt dzēsta</item_delete>
    <item_move>Vienību nevar pārvietot</item_move>
    <item_edit>Vienībai %s labot kļūdu</item_edit>
    <item_occurrance_delete>Nevar dzēst notikumu %s</item_occurrance_delete>
    <item_occurrance_create>Nevar dzēst notikumu</item_occurrance_create>
    <item_exception_delete>Nevar dzēst izņēmumu %s</item_exception_delete>
    <item_exception_create>Nevar izveidot izņēmumu</item_exception_create>
    <item_copy>Nevar kopēt vienību</item_copy>
    <item_copy_multiple>Nevar kopēt vairākas vienības</item_copy_multiple>
    <item_copy_destination>Nevar iegūt mērķa mapi</item_copy_destination>
    <item_copy_destination_type>Nevar kopēt uz cita veida mapi nekā avota mape</item_copy_destination_type>
    <item_count_retrieve>Nevar saskaitīt mapes vienības</item_count_retrieve>
    <item_missing_tag>Trūkst vienības atzīme</item_missing_tag>
    <item_missing_account_id>Trūkst konta ID</item_missing_account_id>
    <item_invalid_account_id>Nepareizs konta ID %s</item_invalid_account_id>
    <item_missing_folder_id>Trūkst mapes ID</item_missing_folder_id>
    <item_invalid_folder_id>Nepareizs mapes ID %s</item_invalid_folder_id>
    <item_missing_item_id>Trūkst vienības ID</item_missing_item_id>
    <item_invalid_item_id>Nepareizs vienības ID %s</item_invalid_item_id>
    <item_invalid_action>Nepareiza vienības darbība</item_invalid_action>
    <login_invalid>Nepareiza lietotāja pieteikšanās %s</login_invalid>
    <login_account_valid>Nepareizs konts %s</login_account_valid>
    <phpmailer_>Vispārīga pasta kļūda, ziņa nav nosūtīta</phpmailer_>
    <phpmailer_smtp_auth>Pastu nevarēja autentificēt, ziņa nav nosūtīta</phpmailer_smtp_auth>
    <phpmailer_smtp_connect>Nevar izveidot savienojumu ar SMTP, ziņa nav nosūtīta</phpmailer_smtp_connect>
    <phpmailer_no_rcpt>Trūkst pasta adresāti, ziņa nav nosūtīta</phpmailer_no_rcpt>
    <phpmailer_mailer_support>Nosūtīšanas programma neatbalsta šo ziņu veidu, ziņa nav nosūtīta</phpmailer_mailer_support>
    <phpmailer_sendmail_send>Sūtāmā pasta sūtīšanas kļūda</phpmailer_sendmail_send>
    <phpmailer_mail_send>E-pasta sūtīšanas kļūda</phpmailer_mail_send>
    <phpmailer_language>Nevar atvērt valodas failu</phpmailer_language>
    <phpmailer_add_attachment>Nevar pievienot failu</phpmailer_add_attachment>
    <phpmailer_encode_file>Nevar kodēt pielikuma failu</phpmailer_encode_file>
    <phpmailer_encode_unknown>Nezināms pielikuma kodējuma veids</phpmailer_encode_unknown>
    <mailparse_empty>Nav avota, lai parsēt</mailparse_empty>
    <mailparse_parser_init>E-pasta analizēšana neizdevās</mailparse_parser_init>
    <mailparse_get_part>Nevar iegūt daļu %s</mailparse_get_part>
    <message_missing_tag>Ziņai trūkst atzīme %s</message_missing_tag>
    <message_missing_account_id>Ziņai trūkst konta ID</message_missing_account_id>
    <message_invald_account>Nepareizs ziņas konta ID</message_invald_account>
    <message_missing_folder_id>Ziņai trūkst mapes ID</message_missing_folder_id>
    <message_invald_folder>Ziņai nepareizs mapes ID</message_invald_folder>
    <message_missing_item_id>Ziņai trūkst vienības ID</message_missing_item_id>
    <message_invalid_action>Ziņas nepareiza darbība</message_invalid_action>
    <message_get_not_allowed>Nevar atjaunināt mapju sarakstu nepietiekamu tiesību dēļ</message_get_not_allowed>
    <message_attachment_type>Nevar analizēt pielikumu %s</message_attachment_type>
    <message_attachment_existence>Nesen augšupielādēts pielikums nav atrasts</message_attachment_existence>
    <rss_channel_exist>Norādītais URL kanāls nevar tikt atvērts %s</rss_channel_exist>
    <rss_invalid_channel>Nevar piekļūt kanālam</rss_invalid_channel>
    <settings_access_denied>Piekļuve liegta</settings_access_denied>
    <settings_missing_tag>Trūkst iestatījumu atzīme %s</settings_missing_tag>
    <settings_duplicity>XML iestatījumu faila formatēšanas kļūda</settings_duplicity>
    <settings_get_domain_file>Nevar izlasīt domēna iestatījumu failu %s</settings_get_domain_file>
    <settings_domain_set>Iestatījumi uzstāda domēna iestatījumus failā %s</settings_domain_set>
    <settings_user_set>Nevar piekļūt lietotāju iestatījumiem failā %. Pārbaudiet atļaujas un pasta mapes.</settings_user_set>
    <settings_public_set>Iestatījumi uzstāda publiskos datus failā %s</settings_public_set>
    <settings_shared_set>Nevar saglabāt koplietojamos kontus</settings_shared_set>
    <settings_owner_set>Nevar uzstādīt īpašnieka iestatījumus</settings_owner_set>
    <session_expired>Sesija %s beigusies</session_expired>
    <session_no_user>Sesijas lietotāja objektu nevar atgūt</session_no_user>
    <smime_no_recipient>SMIME nav saņēmēja</smime_no_recipient>
    <SMTP_data_not_accepted>SMTP dati netiek pieņemti no servera: %s</SMTP_data_not_accepted>
    <SMTP_from_failed>SMTP No: neizdevās (no)</SMTP_from_failed>
    <SMTP_recipients_failed>SMTP adresātiem neizdevās (rcpt)</SMTP_recipients_failed>
    <spellchecker_set_mode>Nevar uzstādīt pareizrakstības pārbaudes režīmu</spellchecker_set_mode>
    <spellchecker_open_dictionary>Nevar atvērt pareizrakstības pārbaudītāja vārdnīcu (dic)</spellchecker_open_dictionary>
    <spellchecker_add_word>Nevar pievienot jaunu vārdu %s vārdnīcai</spellchecker_add_word>
    <spellchecker_missing_check_id>Trūkst vārdu identifikators</spellchecker_missing_check_id>
    <spellchecker_missing_tag>Trūkst atzīmes %s</spellchecker_missing_tag>
    <spellchecker_missing_dictionary_id>Trūkst vārdnīcas identifikators</spellchecker_missing_dictionary_id>
    <spellchecker_missing_word>Trūkstošs vārds</spellchecker_missing_word>
    <upload_tag_missing>Augšupielādēt trūkstošo atzīmi</upload_tag_missing>
    <upload_missing_attribute>Augšupielādēt trūkstošo atribūtu</upload_missing_attribute>
    <upload_attachment_missing>Augšupielādēt trūkstošo pielikumu</upload_attachment_missing>
    <xml_invalid_file_name>XML faila nosaukums ir tukšs</xml_invalid_file_name>
    <xml_xpath_more_nodes_found>XML Xpath atgriež vairāk nekā vienu rezultātu pēc jūsu vaicājuma</xml_xpath_more_nodes_found>
    <xml_node_does_not_exist>XML norādītais mezgls nav atrasts %s</xml_node_does_not_exist>
    <xmlrequest_path>Nepareizs veidnes fails (ceļš)</xmlrequest_path>
    <xmlrequest_access_denied>Piekļuve liegta</xmlrequest_access_denied>
    <xmlrequest_invalid_type>Nepareizs pieprasījuma veids (veids)</xmlrequest_invalid_type>
    <xmlrequest_missing_xmlns>Trūkst nosaukumvietas atribūts</xmlrequest_missing_xmlns>
    <xmlrequest_invalid_sid>Trūkst vai nepareizs SID</xmlrequest_invalid_sid>
    <xmlrequest_missing_tag>Trūkst XMLPieprasījuma atzīmes %s</xmlrequest_missing_tag>
    <xmlrequest_missing_class>Trūkst klases konstruktors</xmlrequest_missing_class>
    <xmlrequest_unkown_format>Nezināms rezultāta formāts %s</xmlrequest_unkown_format>
    <not_implemented>Vēl nav īstenots</not_implemented>
    <logdir_create>Nevar izveidot reģistrēšanās direktoriju %s</logdir_create>
    <api_property_get>Nevar iegūt īpašības priekš %s</api_property_get>
    <wm_disabled>WebKlients ir atslēgts</wm_disabled>
    <gw_init_error>GroupWare inicializācijas kļūda</gw_init_error>
    <default>Izņēmums pēc noklusējuma %s</default>
    <other_accounts_disabled>Izveidot jaunus kontus ir atslēgts</other_accounts_disabled>
    <link_compressed_variable_missing>Kļūda URL, jūs tikāt pārvirzīts uz galvenā ekrāna</link_compressed_variable_missing>
    <login_expired>Pieteikšanās termiņš beidzies, lūdzu, piesakieties vēlreiz</login_expired>
    <account_disabled>Konts ir atslēgts</account_disabled>
    <folder_set_default>Mapi &quot;%s&quot; nevar iestatīt kā pēc noklusējumu</folder_set_default>
    <personality_confirmation_invalid_user>E-pasta adresi nevar apstiprināt: nepareizs lietotājs</personality_confirmation_invalid_user>
    <personality_confirmation_invalid_hashid>E-pasta adresi nevar apstiprināt: nederīgs Hash</personality_confirmation_invalid_hashid>
    <item_blacklist_error>Neizdevās ievietot vienību melnajā sarakstā</item_blacklist_error>
    <item_whitelist_error>Neizdevās ievietot vienību baltajā sarakstā</item_whitelist_error>
    <unverified_signature>Unable to verify message signature</unverified_signature>
    <account_is_guest>Access not allowed for guests</account_is_guest>
  </exceptions>
  <messages>
    <item_selection_cleared>Item selection cleared</item_selection_cleared>
    <logged_out>Jūs esat izgājis</logged_out>
    <message_send_ok>Ziņa nosūtīta</message_send_ok>
    <item_move_ok>Vienība(-s) pārvietota(-s)</item_move_ok>
    <item_copy_ok>Vienība(-s) nokopēta(-s)</item_copy_ok>
    <item_delete_ok>Vienība(-s) dzēsta(-s)</item_delete_ok>
    <item_mark_ok>Vienība(-s) atzīmēta(-s)</item_mark_ok>
    <settings_save_ok>Iestatījumi saglabāti</settings_save_ok>
    <loading_next_message>Ielādē nākamo ziņu</loading_next_message>
    <loading_prev_message>Ielādē iepriekšējo ziņu</loading_prev_message>
    <loading_next_page>Ielādē nākamo lappusi</loading_next_page>
    <loading_prev_page>Ielādē iepriekšējo lappusi</loading_prev_page>
    <loading_next_month>Ielādē nākamo mēnesi</loading_next_month>
    <loading_prev_month>Ielādē iepriekšējo mēnesi</loading_prev_month>
    <loading_next_week>Ielādē nākamo nedēļu</loading_next_week>
    <loading_prev_week>Ielādē iepriekšējo nedēļu</loading_prev_week>
    <loading_next_day>Ielādē nākamo dienu</loading_next_day>
    <loading_prev_day>Ielādē iepriekšējo dienu</loading_prev_day>
    <password_change_ok>Parole nomainīta</password_change_ok>
    <item_whitelist_ok>Vienība tika pievienota baltajam sarakstam</item_whitelist_ok>
    <item_blacklist_ok>Vienība tika pievienota melnajam sarakstam</item_blacklist_ok>
    <folder_set_default_ok>Mape iestatīta kā pēc noklusējuma</folder_set_default_ok>
    <subscribe_account_ok>Konts ir pierakstīts</subscribe_account_ok>
    <subscribe_folder_ok>Mape ir pierakstīta</subscribe_folder_ok>
    <item_decline_ok>Vienība noraidīta</item_decline_ok>
    <access_granted>Jums ir piešķirta piekļuve &quot;%s&quot; ar &quot;%s&quot;.</access_granted>
    <message_save_ok>Ziņa saglabāta</message_save_ok>
    <item_accept_ok>Item accepted</item_accept_ok>
  </messages>
</language>
